AUTHORS
LICENSE
README.md
README.rst
setup.py
NuGridpy.egg-info/PKG-INFO
NuGridpy.egg-info/SOURCES.txt
NuGridpy.egg-info/dependency_links.txt
NuGridpy.egg-info/requires.txt
NuGridpy.egg-info/top_level.txt
nugridpy/__init__.py
nugridpy/ascii_table.py
nugridpy/astronomy.py
nugridpy/data_plot.py
nugridpy/grain.py
nugridpy/h5T.py
nugridpy/mesa.py
nugridpy/nugridse.py
nugridpy/ppn.py
nugridpy/utils.py
nugridpy/regression_tests/__init__.py
nugridpy/regression_tests/benoittest.py
nugridpy/regression_tests/selftest.py
nugridpy/regression_tests/ImageCompare/__init__.py
nugridpy/regression_tests/ImageCompare/abu_chart.py
nugridpy/regression_tests/ImageCompare/compare_image_entropy.py
nugridpy/regression_tests/tempdir/__init__.py
nugridpy/regression_tests/tempdir/tempfile_.py