Metadata-Version: 1.1
Name: NuGridpy
Version: 0.7.5
Summary: Python tools for NuGrid
Home-page: https://nugrid.github.io/NuGridPy
Author: NuGrid Team
Author-email: fherwig@uvic.ca
License: BSD 3-clause
Platform: Linux
Platform: Windows
Platform: OS X
Classifier: Development Status :: 4 - Beta
Classifier: Environment :: Console
Classifier: Framework :: IPython
Classifier: Intended Audience :: Science/Research
Classifier: License :: OSI Approved :: BSD License
Classifier: Natural Language :: English
Classifier: Operating System :: OS Independent
Classifier: Programming Language :: Python :: 2.7
Classifier: Programming Language :: Python :: 3.5
Classifier: Topic :: Scientific/Engineering :: Astronomy
Classifier: Topic :: Scientific/Engineering :: Visualization
